fr24sdk/__init__.py
fr24sdk/client.py
fr24sdk/exceptions.py
fr24sdk/transport.py
fr24sdk/models/.gitkeep
fr24sdk/models/__init__.py
fr24sdk/models/airline.py
fr24sdk/models/airport.py
fr24sdk/models/flight.py
fr24sdk/models/geographic.py
fr24sdk/models/regex_patterns.py
fr24sdk/models/usage.py
fr24sdk/resources/.gitkeep
fr24sdk/resources/__init__.py
fr24sdk/resources/airlines.py
fr24sdk/resources/airports.py
fr24sdk/resources/flight_summary.py
fr24sdk/resources/flight_tracks.py
fr24sdk/resources/usage.py
fr24sdk/resources/historic/events.py
fr24sdk/resources/historic/positions.py
fr24sdk/resources/live/positions.py
fr24sdk/validators/.gitkeep
fr24sdk-0.2.0.dist-info/METADATA
fr24sdk-0.2.0.dist-info/WHEEL
fr24sdk-0.2.0.dist-info/licenses/LICENSE
fr24sdk-0.2.0.dist-info/RECORD
