Metadata-Version: 2.4
Name: fr24sdk
Version: 0.2.0
Summary: Python SDK for the Flightradar24 API
Project-URL: Homepage, https://github.com/flightradar24/fr24api-sdk-python
Project-URL: Documentation, https://github.com/flightradar24/fr24api-sdk-python/blob/main/docs/README.md
Project-URL: Repository, https://github.com/flightradar24/fr24api-sdk-python
Project-URL: Changelog, https://github.com/flightradar24/fr24api-sdk-python/blob/main/CHANGELOG.md
Author-email: Damian Szumski <damian.szumski@fr24.com>
License: MIT License
License-File: LICENSE
Keywords: FR24,api,aviation,flightradar24,sdk
Classifier: Development Status :: 3 - Alpha
Classifier: Intended Audience :: Developers
Classifier: License :: OSI Approved :: MIT License
Classifier: Operating System :: OS Independent
Classifier: Programming Language :: Python :: 3
Classifier: Programming Language :: Python :: 3.9
Classifier: Programming Language :: Python :: 3.10
Classifier: Programming Language :: Python :: 3.11
Classifier: Programming Language :: Python :: 3.12
Classifier: Topic :: Software Development :: Libraries :: Python Modules
Requires-Python: >=3.9
Requires-Dist: exceptiongroup; python_version < '3.11'
Requires-Dist: httpx<0.28,>=0.26
Requires-Dist: pydantic<2.11.0,>=2.10.6
Requires-Dist: tenacity<9.0,>=8.2
